[
  {
    "_id": {
      "$oid": "68ceac6281436dd108e55f63"
    },
    "firstName": "Aung",
    "lastName": "Thu Hein",
    "email": "agthuhein1991@gmail.com",
    "address": "216 PETIR ROAD\n12-415",
    "phone": "98804670",
    "message": "",
    "pet": {
      "$oid": "68ce984063265f776517e4b0"
    },
    "user": {
      "$oid": "68cd1e670d6371dd17839520"
    },
    "status": "rejected",
    "createdAt": {
      "$date": "2025-08-20T13:30:10.143Z"
    },
    "updatedAt": {
      "$date": "2025-08-20T13:30:57.692Z"
    },
    "__v": 0
  },
  {
    "_id": {
      "$oid": "68ceb26b100007b1ef6d372c"
    },
    "firstName": "Aung",
    "lastName": "Thu Hein",
    "email": "agthuhein1991@gmail.com",
    "address": "216 PETIR ROAD\n12-415",
    "phone": "98804670",
    "message": "",
    "pet": {
      "$oid": "68cea163e301149858cbc606"
    },
    "user": {
      "$oid": "68cd1e670d6371dd17839520"
    },
    "status": "approved",
    "createdAt": {
      "$date": "2025-08-20T13:55:55.060Z"
    },
    "updatedAt": {
      "$date": "2025-08-20T13:56:01.364Z"
    },
    "__v": 0
  },
  {
    "_id": {
      "$oid": "68ced4e73b22679c4c3927cf"
    },
    "firstName": "Aung",
    "lastName": "Thu Hein",
    "email": "agthuhein.mm@gmail.com",
    "address": "216 PETIR ROAD\n12-415",
    "phone": "98804670",
    "message": "",
    "pet": {
      "$oid": "68ced4af3b22679c4c3927b6"
    },
    "user": {
      "$oid": "68cd1e670d6371dd17839520"
    },
    "status": "approved",
    "createdAt": {
      "$date": "2025-09-20T16:23:03.059Z"
    },
    "updatedAt": {
      "$date": "2025-09-20T16:23:30.826Z"
    },
    "__v": 0
  },
  {
    "_id": {
      "$oid": "68ced5e93b22679c4c39281b"
    },
    "firstName": "Aung",
    "lastName": "Thu Hein",
    "email": "agthuhein.mm@gmail.com",
    "address": "216 PETIR ROAD\n12-415",
    "phone": "98804670",
    "message": "",
    "pet": {
      "$oid": "68ced48d3b22679c4c3927b1"
    },
    "user": {
      "$oid": "68cd1e670d6371dd17839520"
    },
    "status": "pending",
    "createdAt": {
      "$date": "2025-09-20T16:27:21.234Z"
    },
    "updatedAt": {
      "$date": "2025-09-20T16:27:21.234Z"
    },
    "__v": 0
  },
  {
    "_id": {
      "$oid": "68d10fb299ca7ff22bbea85a"
    },
    "firstName": "Aung",
    "lastName": "Thu Hein",
    "email": "aungthuhein.bm@gmail.com",
    "address": "Karlsruher Str. 14\nGermany",
    "phone": "015218481833",
    "message": "",
    "pet": {
      "$oid": "68ce9aecb24d0a27f0364ab5"
    },
    "user": {
      "$oid": "68d10176565e02ca4abaf313"
    },
    "status": "rejected",
    "createdAt": {
      "$date": "2025-09-22T08:58:26.840Z"
    },
    "updatedAt": {
      "$date": "2025-09-22T14:44:45.928Z"
    },
    "__v": 0
  },
  {
    "_id": {
      "$oid": "68d153a3f66633533bf23acd"
    },
    "firstName": "Aung",
    "lastName": "Thu Hein",
    "email": "agthuhein.mm@gmail.com",
    "address": "Karlsruher Str. 14\nGermany",
    "phone": "015218481833",
    "message": "",
    "pet": {
      "$oid": "68ced46f3b22679c4c3927ac"
    },
    "user": {
      "$oid": "68cd1e670d6371dd17839520"
    },
    "status": "rejected",
    "createdAt": {
      "$date": "2025-08-22T13:48:19.987Z"
    },
    "updatedAt": {
      "$date": "2025-09-22T14:44:53.446Z"
    },
    "__v": 0
  },
  {
    "_id": {
      "$oid": "68d1cbf420f91827e4d97969"
    },
    "firstName": "Aung",
    "lastName": "Thu Hein",
    "email": "agthuhein1991@gmail.com",
    "address": "Karlsruher Str. 14\nGermany",
    "phone": "015218481833",
    "message": "",
    "pet": {
      "$oid": "68ce984063265f776517e4b0"
    },
    "user": {
      "$oid": "68d1b5413123d6bd306bc9cf"
    },
    "status": "canceled",
    "createdAt": {
      "$date": "2025-09-22T22:21:40.874Z"
    },
    "updatedAt": {
      "$date": "2025-09-23T07:06:18.833Z"
    },
    "__v": 0
  }
]
